openmath/__init__.py
openmath/convert.py
openmath/convert_pickle.py
openmath/decoder.py
openmath/encoder.py
openmath/openmath.py
openmath/xml.py
openmath-0.3.0.dist-info/METADATA
openmath-0.3.0.dist-info/RECORD
openmath-0.3.0.dist-info/WHEEL
openmath-0.3.0.dist-info/top_level.txt
tests/__init__.py
tests/test_convert.py
tests/test_decoder.py
tests/test_encoder.py
tests/test_openmath.py
tests/utils.py
