Metadata-Version: 2.1
Name: openmath
Version: 0.3.0
Summary: Object implementation of the OpenMath standard
Home-page: https://github.com/OpenMath/py-openmath
Author: Luca De Feo, Tom Wiesing
Author-email: UNKNOWN
License: MIT
Keywords: openmath
Platform: UNKNOWN
Classifier: Intended Audience :: Science/Research
Classifier: License :: OSI Approved :: MIT License
Classifier: Programming Language :: Python :: 2
Classifier: Programming Language :: Python :: 3
Requires-Dist: lxml
Requires-Dist: six
